setuptools_certificate/__init__.py
setuptools_certificate/version.py
setuptools_certificate-0.0.7.dist-info/LICENSE
setuptools_certificate-0.0.7.dist-info/METADATA
setuptools_certificate-0.0.7.dist-info/WHEEL
setuptools_certificate-0.0.7.dist-info/entry_points.txt
setuptools_certificate-0.0.7.dist-info/top_level.txt
setuptools_certificate-0.0.7.dist-info/RECORD
