Metadata-Version: 2.1
Name: setuptools-certificate
Version: 0.0.7
Summary: A setuptools extension for signed certificate and public key metadata for verifying contents of pip modules.
Home-page: https://github.com/guzman-raphael/setuptools_certificate
Author: Raphael Guzman
Author-email: raphael.h.guzman@gmail.com
License: UNKNOWN
Platform: UNKNOWN
Classifier: Programming Language :: Python :: 3
Classifier: License :: OSI Approved :: MIT License
Classifier: Operating System :: OS Independent
Requires-Dist: cryptography
Requires-Dist: otumat
